rest_requests/__about__.py
rest_requests/__init__.py
rest_requests/json.py
rest_requests-2.1.0.dist-info/METADATA
rest_requests-2.1.0.dist-info/WHEEL
rest_requests-2.1.0.dist-info/licenses/LICENSE.txt
rest_requests-2.1.0.dist-info/RECORD
