Metadata-Version: 2.4
Name: rest-requests
Version: 2.1.0
Summary: Lightweight asynchronous REST API requests. JSON bodies only. Proxy support.
Project-URL: Documentation, https://github.com/Kwasniok/pypi-rest-requests#readme
Project-URL: Issues, https://github.com/Kwasniok/pypi-rest-requests/issues
Project-URL: Source, https://github.com/Kwasniok/pypi-rest-requests
Author-email: Kwasniok <Kwasniok@users.noreply.github.com>, AlexanderKlemps <AlexanderKlemps@users.noreply.github.com>
Maintainer-email: Kwasniok <Kwasniok@users.noreply.github.com>
License-Expression: CC-BY-SA-4.0
License-File: LICENSE.txt
Keywords: api,rest
Classifier: Development Status :: 4 - Beta
Classifier: Programming Language :: Python
Classifier: Programming Language :: Python :: 3.10
Classifier: Programming Language :: Python :: 3.11
Classifier: Programming Language :: Python :: 3.12
Classifier: Programming Language :: Python :: 3.13
Classifier: Programming Language :: Python :: 3.14
Requires-Python: >=3.10
Requires-Dist: aiohttp-socks>=0.10
Requires-Dist: aiohttp>=3.13
